graph_mapper/__init__.py
graph_mapper/mapper.py
graph_mapper/test_mapper.py
graph_mapper-1.0.dev1.dist-info/METADATA
graph_mapper-1.0.dev1.dist-info/RECORD
graph_mapper-1.0.dev1.dist-info/WHEEL
graph_mapper-1.0.dev1.dist-info/top_level.txt
