Metadata-Version: 2.1
Name: graph-mapper
Version: 1.0.dev1
Summary: Uses graph partitioning techniques to assign data to locations on a rectangle
Home-page: http://github.com/singular-value/graph_mapper
Author: Pranav Gokhale
Author-email: pranavgokhale@uchicago.edu
License: MIT
Platform: UNKNOWN
Requires-Python: >=3
Requires-Dist: metis
